mop/__init__.py
mop/logger.py
mop/monitor.py
mop/utils.py
python_mop-0.0.1.dist-info/LICENSE
python_mop-0.0.1.dist-info/METADATA
python_mop-0.0.1.dist-info/WHEEL
python_mop-0.0.1.dist-info/top_level.txt
python_mop-0.0.1.dist-info/RECORD
