Metadata-Version: 2.1
Name: python-mop
Version: 0.0.1
Summary: python toolkit for monitor-oriented programming.
Home-page: https://github.com/CDU-Ge/python_mop
Author: CDU-Ge
Author-email: cosplox@outlook.com
License: MIT LICENSE
License-File: LICENSE
